LICENSE
MANIFEST.in
README.rst
pyproject.toml
setup.py
iced/__init__.py
iced/_filter_.pyx
iced/filter.py
iced/setup.py
iced.egg-info/PKG-INFO
iced.egg-info/SOURCES.txt
iced.egg-info/dependency_links.txt
iced.egg-info/entry_points.txt
iced.egg-info/requires.txt
iced.egg-info/top_level.txt
iced/datasets/__init__.py
iced/datasets/base.py
iced/datasets/setup.py
iced/datasets/data/duan2009/duan.SC.10000.raw_sub.bed
iced/datasets/data/duan2009/duan.SC.10000.raw_sub.matrix
iced/datasets/data/servant2018/simulation_3.bed
iced/datasets/data/servant2018/simulation_3.mat
iced/datasets/tests/test_base.py
iced/io/__init__.py
iced/io/_io_pandas.py
iced/io/setup.py
iced/io/tests/test_io.py
iced/normalization/__init__.py
iced/normalization/_ca_utils.py
iced/normalization/_normalization_.pyx
iced/normalization/tests/test_ca_utils.py
iced/normalization/tests/test_normalization.py
iced/random/__init__.py
iced/random/tests/test_init.py
iced/scripts/ice.py
iced/tests/test_filter.py
iced/utils/__init__.py
iced/utils/_genome.py
iced/utils/_validation.py
iced/utils/validation.py
iced/utils/tests/test_genome.py
iced/utils/tests/test_validation.py