Metadata-Version: 2.1
Name: iced
Version: 0.6.0
Summary: ICE normalization
Author-email: Nelle Varoquaux <nelle.varoquaux@gmail.com>
Maintainer-email: Nelle Varoquaux <nelle.varoquaux@gmail.com>
Project-URL: Homepage, https://hiclib.github.io/iced/
Project-URL: Documentation, https://hiclib.github.io/iced/documentation.html
Project-URL: Repository, https://github.com/hiclib/iced.git
Project-URL: Issues, https://github.com/hiclib/iced/issues
Project-URL: Download, https://github.com/hiclib/iced/releases
Keywords: iced,hi-c,chromatin
Classifier: Development Status :: 3 - Alpha
Classifier: Intended Audience :: Science/Research
Classifier: Intended Audience :: Developers
Classifier: Programming Language :: Python
Classifier: Topic :: Utilities
Classifier: Topic :: Software Development
Classifier: Topic :: Scientific/Engineering
Classifier: Operating System :: Microsoft :: Windows
Classifier: Operating System :: POSIX
Classifier: Operating System :: Unix
Classifier: Operating System :: MacOS
Requires-Python: >=3.9
License-File: LICENSE
Requires-Dist: numpy>=1.16.0
Requires-Dist: scipy>=0.19.0
